{
  "id": "level-avatar",
  "movieId": "movie-avatar",
  "difficulty": "medium",
  "image": "/images/avatar.png",
  "width": 1536,
  "height": 1024,
  "acceptedAnswers": [
    "Аватар",
    "Avatar"
  ],
  "revealRegions": [
    {
      "id": "область-1",
      "name": "Область 1",
      "polygon": [
        [
          1522,
          626
        ],
        [
          1128,
          621
        ],
        [
          1003,
          643
        ],
        [
          796,
          853
        ],
        [
          924,
          989
        ],
        [
          1519,
          1015
        ]
      ],
      "displayOrder": 1,
      "scorePenalty": 80,
      "kind": "area"
    },
    {
      "id": "область-2",
      "name": "Область 2",
      "polygon": [
        [
          623,
          932
        ],
        [
          490,
          561
        ],
        [
          289,
          405
        ],
        [
          23,
          419
        ],
        [
          3,
          1009
        ],
        [
          558,
          1015
        ]
      ],
      "displayOrder": 2,
      "scorePenalty": 120,
      "kind": "area"
    },
    {
      "id": "область-3",
      "name": "Область 3",
      "polygon": [
        [
          930,
          221
        ],
        [
          1034,
          371
        ],
        [
          779,
          510
        ],
        [
          751,
          564
        ],
        [
          757,
          626
        ],
        [
          853,
          660
        ],
        [
          1119,
          652
        ],
        [
          1329,
          541
        ],
        [
          1301,
          473
        ],
        [
          1275,
          400
        ],
        [
          1210,
          266
        ],
        [
          1074,
          187
        ],
        [
          975,
          187
        ]
      ],
      "displayOrder": 3,
      "scorePenalty": 180,
      "kind": "area"
    },
    {
      "id": "область-4",
      "name": "Область 4",
      "polygon": [
        [
          451,
          85
        ],
        [
          836,
          3
        ],
        [
          1533,
          0
        ],
        [
          1533,
          496
        ],
        [
          465,
          417
        ]
      ],
      "displayOrder": 4,
      "scorePenalty": 260,
      "kind": "area"
    },
    {
      "id": "full",
      "name": "Полное изображение",
      "polygon": [],
      "displayOrder": 5,
      "scorePenalty": 260,
      "kind": "full_image"
    }
  ]
}
